donkeycar/__init__.py
donkeycar/config.py
donkeycar/log.py
donkeycar/memory.py
donkeycar/vehicle.py
donkeycar/management/__init__.py
donkeycar/management/base.py
donkeycar/management/tub.py
donkeycar/parts/__init__.py
donkeycar/parts/actuator.py
donkeycar/parts/camera.py
donkeycar/parts/clock.py
donkeycar/parts/controller.py
donkeycar/parts/datastore.py
donkeycar/parts/gluon.py
donkeycar/parts/gluon_dataset.py
donkeycar/parts/gluon_model.py
donkeycar/parts/gluon_trainer.py
donkeycar/parts/keras.py
donkeycar/parts/simulation.py
donkeycar/parts/transform.py
donkeycar/parts/web_controller/__init__.py
donkeycar/parts/web_controller/web.py
donkeycar/parts/web_controller/templates/base.html
donkeycar/parts/web_controller/templates/vehicle.html
donkeycar/parts/web_controller/templates/static/jquery-3.1.1.min.js
donkeycar/parts/web_controller/templates/static/main.js
donkeycar/parts/web_controller/templates/static/nipple.js
donkeycar/parts/web_controller/templates/static/style.css
donkeycar/parts/web_controller/templates/static/bootstrap/3.3.7/css/bootstrap.min.css
donkeycar/parts/web_controller/templates/static/bootstrap/3.3.7/fonts/glyphicons-halflings-regular.ttf
donkeycar/parts/web_controller/templates/static/bootstrap/3.3.7/fonts/glyphicons-halflings-regular.woff
donkeycar/parts/web_controller/templates/static/bootstrap/3.3.7/fonts/glyphicons-halflings-regular.woff2
donkeycar/parts/web_controller/templates/static/bootstrap/3.3.7/js/bootstrap.min.js
donkeycar/parts/web_controller/templates/static/ui/1.12.1/jquery-ui.min.js
donkeycar/templates/config_defaults.py
donkeycar/templates/donkey2.py
donkeycar/templates/square.py
donkeycar/tests/__init__.py
donkeycar/tests/setup.py
donkeycar/tests/test_actuator.py
donkeycar/tests/test_keras.py
donkeycar/tests/test_management.py
donkeycar/tests/test_memory.py
donkeycar/tests/test_parts.py
donkeycar/tests/test_scripts.py
donkeycar/tests/test_sensors.py
mxnet_donkeycar-1.0.dist-info/METADATA
mxnet_donkeycar-1.0.dist-info/RECORD
mxnet_donkeycar-1.0.dist-info/WHEEL
mxnet_donkeycar-1.0.dist-info/entry_points.txt
mxnet_donkeycar-1.0.dist-info/top_level.txt
